pyskoob/__init__.py
pyskoob/auth.py
pyskoob/authors.py
pyskoob/books.py
pyskoob/client.py
pyskoob/exceptions.py
pyskoob/profile.py
pyskoob/publishers.py
pyskoob/users.py
pyskoob/http/__init__.py
pyskoob/http/client.py
pyskoob/http/httpx.py
pyskoob/internal/__init__.py
pyskoob/internal/async_authenticated.py
pyskoob/internal/async_base.py
pyskoob/internal/authenticated.py
pyskoob/internal/base.py
pyskoob/models/__init__.py
pyskoob/models/author.py
pyskoob/models/book.py
pyskoob/models/enums.py
pyskoob/models/pagination.py
pyskoob/models/publisher.py
pyskoob/models/user.py
pyskoob/parsers/__init__.py
pyskoob/parsers/authors.py
pyskoob/parsers/books.py
pyskoob/parsers/publishers.py
pyskoob/utils/__init__.py
pyskoob/utils/bs4_utils.py
pyskoob/utils/rate_limiter.py
pyskoob/utils/skoob_parser_utils.py
pyskoob-0.2.0.dist-info/licenses/LICENSE
pyskoob-0.2.0.dist-info/METADATA
pyskoob-0.2.0.dist-info/WHEEL
pyskoob-0.2.0.dist-info/top_level.txt
pyskoob-0.2.0.dist-info/RECORD
