Metadata-Version: 2.4
Name: pyskoob
Version: 0.2.0
Summary: Python client for the Skoob website handling authentication and HTML parsing
Keywords: skoob,books,client,api,scraping
Requires-Python: >=3.11
License-File: LICENSE
Requires-Dist: bs4>=0.0.2
Requires-Dist: httpx>=0.28.1
Requires-Dist: pydantic>=2.11.7
Provides-Extra: dev
Requires-Dist: pytest>=8.4.1; extra == "dev"
Requires-Dist: pytest-cov>=6.2.1; extra == "dev"
Requires-Dist: requests>=2.32.4; extra == "dev"
Requires-Dist: ruff>=0.12.4; extra == "dev"
Provides-Extra: docs
Requires-Dist: mkdocs>=1.6.0; extra == "docs"
Requires-Dist: mkdocs-material<10.0,>=9.6.0; extra == "docs"
Requires-Dist: mkdocstrings[python]>=0.24.0; extra == "docs"
Dynamic: license-file
